odoo/addons/followers_mass_invoice_mailing/README.rst
odoo/addons/followers_mass_invoice_mailing/__init__.py
odoo/addons/followers_mass_invoice_mailing/__manifest__.py
odoo/addons/followers_mass_invoice_mailing/models/__init__.py
odoo/addons/followers_mass_invoice_mailing/models/account_invoice_send.py
odoo/addons/followers_mass_invoice_mailing/static/description/icon.png
odoo14_addon_followers_mass_invoice_mailing-14.0.1.0.1.dev1.dist-info/METADATA
odoo14_addon_followers_mass_invoice_mailing-14.0.1.0.1.dev1.dist-info/WHEEL
odoo14_addon_followers_mass_invoice_mailing-14.0.1.0.1.dev1.dist-info/top_level.txt
odoo14_addon_followers_mass_invoice_mailing-14.0.1.0.1.dev1.dist-info/RECORD
